{
  "variants": {
    "enabled=false,facing=down": {
      "model": "littlelogistics:block/rapid_hopper",
      "y": 270
    },
    "enabled=false,facing=east": {
      "model": "littlelogistics:block/rapid_hopper_side",
      "y": 90
    },
    "enabled=false,facing=north": {
      "model": "littlelogistics:block/rapid_hopper_side"
    },
    "enabled=false,facing=south": {
      "model": "littlelogistics:block/rapid_hopper_side",
      "y": 180
    },
    "enabled=false,facing=west": {
      "model": "littlelogistics:block/rapid_hopper_side",
      "y": 270
    },
    "enabled=true,facing=down": {
      "model": "littlelogistics:block/rapid_hopper",
      "y": 270
    },
    "enabled=true,facing=east": {
      "model": "littlelogistics:block/rapid_hopper_side",
      "y": 90
    },
    "enabled=true,facing=north": {
      "model": "littlelogistics:block/rapid_hopper_side"
    },
    "enabled=true,facing=south": {
      "model": "littlelogistics:block/rapid_hopper_side",
      "y": 180
    },
    "enabled=true,facing=west": {
      "model": "littlelogistics:block/rapid_hopper_side",
      "y": 270
    }
  }
}